[
  {
    "py/object": "model.contact.Contact",
    "id": null,
    "first_name": "nameu",
    "last_name": "H",
    "address": "F67maDjtaScvN",
    "all_phones_from_home_page": null,
    "homephone": null,
    "workphone": null,
    "mobile": "+69911740912",
    "secondaryphone": null,
    "all_emails": null,
    "email": "cU9y2t@mail.com",
    "email2": null,
    "email3": null,
    "bday": 12,
    "bmonth": "November",
    "byear": 1974,
    "notes": "NkRGYJcvinZfFOcKc"
  },
  {
    "py/object": "model.contact.Contact",
    "id": null,
    "first_name": "nameU",
    "last_name": "2",
    "address": "1MeXqo9cvq6",
    "all_phones_from_home_page": null,
    "homephone": null,
    "workphone": null,
    "mobile": "+273328900",
    "secondaryphone": null,
    "all_emails": null,
    "email": "K2@mail.com",
    "email2": null,
    "email3": null,
    "bday": 20,
    "bmonth": "December",
    "byear": 1993,
    "notes": "H3IwQLGR8Ls"
  },
  {
    "py/object": "model.contact.Contact",
    "id": null,
    "first_name": "nameOX",
    "last_name": "Zy",
    "address": "Sf1MEc8HuOuxvY",
    "all_phones_from_home_page": null,
    "homephone": null,
    "workphone": null,
    "mobile": "+94722768342",
    "secondaryphone": null,
    "all_emails": null,
    "email": "f2@mail.com",
    "email2": null,
    "email3": null,
    "bday": 8,
    "bmonth": "November",
    "byear": 2018,
    "notes": "cPLYQqL"
  },
  {
    "py/object": "model.contact.Contact",
    "id": null,
    "first_name": "name4miN",
    "last_name": "EijFo3Qn",
    "address": "AD4Gk4C3UEr4rT",
    "all_phones_from_home_page": null,
    "homephone": null,
    "workphone": null,
    "mobile": "+8990576370",
    "secondaryphone": null,
    "all_emails": null,
    "email": "Qdq@mail.com",
    "email2": null,
    "email3": null,
    "bday": 5,
    "bmonth": "June",
    "byear": 1976,
    "notes": "fRNE"
  },
  {
    "py/object": "model.contact.Contact",
    "id": null,
    "first_name": "nameIZTA",
    "last_name": "",
    "address": "akVZWrh2o",
    "all_phones_from_home_page": null,
    "homephone": null,
    "workphone": null,
    "mobile": "+04149866",
    "secondaryphone": null,
    "all_emails": null,
    "email": "14M2qe@mail.com",
    "email2": null,
    "email3": null,
    "bday": 28,
    "bmonth": "July",
    "byear": 2000,
    "notes": "j"
  }
]